AE_Toolbox/__init__.py
AE_Toolbox/common.py
AE_Toolbox-0.2.0.dist-info/LICENSE
AE_Toolbox-0.2.0.dist-info/METADATA
AE_Toolbox-0.2.0.dist-info/WHEEL
AE_Toolbox-0.2.0.dist-info/top_level.txt
AE_Toolbox-0.2.0.dist-info/RECORD
