Metadata-Version: 2.1
Name: AE-Toolbox
Version: 0.2.0
Summary: A toolbox for adversarial examples
Author: test
Author-email: 1429030919@qq.com
Classifier: Programming Language :: Python :: 3
Classifier: License :: OSI Approved :: MIT License
Classifier: Operating System :: OS Independent
Requires-Python: >=3.8
License-File: LICENSE
Requires-Dist: foolbox (==3.3.3)
Requires-Dist: matplotlib (==3.1.2)
Requires-Dist: torch (==1.13.0)
Requires-Dist: torchvision (==0.14.0)
